centraldogma/__init__.py
centraldogma/base_client.py
centraldogma/content_service.py
centraldogma/dogma.py
centraldogma/exceptions.py
centraldogma/project_service.py
centraldogma/query.py
centraldogma/repository_service.py
centraldogma/repository_watcher.py
centraldogma/util.py
centraldogma/watcher.py
centraldogma/data/__init__.py
centraldogma/data/change.py
centraldogma/data/commit.py
centraldogma/data/constants.py
centraldogma/data/content.py
centraldogma/data/creator.py
centraldogma/data/entry.py
centraldogma/data/merge_source.py
centraldogma/data/merged_entry.py
centraldogma/data/project.py
centraldogma/data/push_result.py
centraldogma/data/repository.py
centraldogma/data/revision.py
centraldogma_python-0.6.0.dist-info/licenses/LICENSE.txt
centraldogma_python-0.6.0.dist-info/METADATA
centraldogma_python-0.6.0.dist-info/WHEEL
centraldogma_python-0.6.0.dist-info/top_level.txt
centraldogma_python-0.6.0.dist-info/RECORD
