Metadata-Version: 2.4
Name: centraldogma-python
Version: 0.6.0
Summary: Python client library for Central Dogma
Author-email: Central Dogma Team <dl_centraldogma@linecorp.com>
Project-URL: Homepage, https://github.com/line/centraldogma-python
Project-URL: Documentation, https://line.github.io/centraldogma-python
Project-URL: Repository, https://github.com/line/centraldogma-python.git
Project-URL: Issues, https://github.com/line/centraldogma-python/issues
Classifier: Development Status :: 4 - Beta
Classifier: Intended Audience :: Developers
Classifier: License :: OSI Approved :: Apache Software License
Classifier: Operating System :: OS Independent
Classifier: Programming Language :: Python
Classifier: Programming Language :: Python :: 3
Classifier: Programming Language :: Python :: 3.9
Classifier: Programming Language :: Python :: 3.10
Classifier: Programming Language :: Python :: 3.11
Classifier: Programming Language :: Python :: 3.12
Classifier: Programming Language :: Python :: 3.13
Classifier: Topic :: Software Development :: Libraries :: Python Modules
Requires-Python: >=3.9
License-File: LICENSE.txt
Requires-Dist: dataclasses-json<0.7.0,>=0.6.7
Requires-Dist: httpx[http2]<1.0.0,>=0.27.2
Requires-Dist: marshmallow<4.0.0,>=3.23.0
Requires-Dist: pydantic<3.0.0,>=2.9.2
Requires-Dist: python-dateutil<3.0.0,>=2.9.0.post0
Requires-Dist: tenacity<10.0.0,>=9.0.0
Provides-Extra: dev
Requires-Dist: black; extra == "dev"
Requires-Dist: codecov; extra == "dev"
Requires-Dist: pytest; extra == "dev"
Requires-Dist: pytest-cov; extra == "dev"
Requires-Dist: pytest-mock; extra == "dev"
Requires-Dist: respx; extra == "dev"
Provides-Extra: docs
Requires-Dist: sphinx_rtd_theme; extra == "docs"
Dynamic: license-file
